pagecrawler/__init__.py
pagecrawler/headers.py
pagecrawler/view.py
pagecrawler/webscraping.py
pagecrawler-1.1.2.dist-info/LICENSE
pagecrawler-1.1.2.dist-info/METADATA
pagecrawler-1.1.2.dist-info/WHEEL
pagecrawler-1.1.2.dist-info/RECORD
