Metadata-Version: 2.3
Name: pagecrawler
Version: 1.1.2
Summary: A simple webscraper
Author: No1d3a
Author-email: furids11@gmail.com
Requires-Python: >=3.11,<4.0
Classifier: Programming Language :: Python :: 3
Classifier: Programming Language :: Python :: 3.11
Classifier: Programming Language :: Python :: 3.12
Classifier: Programming Language :: Python :: 3.13
Requires-Dist: beautifulsoup4 (>=4.12.3,<5.0.0)
Requires-Dist: requests (>=2.32.3,<3.0.0)
Requires-Dist: selenium (==4.21.0)
Requires-Dist: selenium_stealth (==1.0.6)
Requires-Dist: webdriver_manager (==4.0.1)
